mypacked/__init__.py
mypacked-0.0.1.dist-info/LICENSE.txt
mypacked-0.0.1.dist-info/METADATA
mypacked-0.0.1.dist-info/WHEEL
mypacked-0.0.1.dist-info/top_level.txt
mypacked-0.0.1.dist-info/RECORD
